[
    {
        "id": 1,
        "type": 1,
        "question":  "1. تزيد الأنشطة الموجودة في البيئة من استيعاب ما اتعلمه.",
        "ansA": "موافق بشدة .",
        "ansB": "موافق.",
        "ansC": "محايد.",
        "ansD": "غير موافق.",
        "ansE": "غير موافق بشدة.",
        "correct": "",
        "selected": ""
    },
    {
        "id": 2,
        "type": 1,
        "question": "2. يصعب علي الوصول بسرعه لمهام التعلم.",
        "ansA": "موافق بشدة .",
        "ansB": "موافق.",
        "ansC": "محايد.",
        "ansD": "غير موافق.",
        "ansE": "غير موافق بشدة.",
        "correct": "",
        "selected": ""
    },
    {
        "id": 3,
        "type": 1,
        "question": "3. احصل من خلال استخدام بيئة التعلم علي درجات أقل من المعدل المطلوب.",
        "ansA": "موافق بشدة .",
        "ansB": "موافق.",
        "ansC": "محايد.",
        "ansD": "غير موافق.",
        "ansE": "غير موافق بشدة.",
        "correct": "",
        "selected": ""
    },
    {
        "id": 4,
        "type": 1,
        "question": "4. بيئة التعلم لا تقدم لي التغذية الراجعة التي تشجعني علي اكمال المهام المطلوبة.",
        "ansA": "موافق بشدة .",
        "ansB": "موافق.",
        "ansC": "محايد.",
        "ansD": "غير موافق.",
        "ansE": "غير موافق بشدة.",
        "correct": "",
        "selected": ""
    },
    {
        "id": 5,
        "type": 1,
        "question": "5. أفضل قضاء الوقت في حل الأنشطه المقدمة لى عبر البيئة عن أي شيء آخر.",
        "ansA": "موافق بشدة .",
        "ansB": "موافق.",
        "ansC": "محايد.",
        "ansD": "غير موافق.",
        "ansE": "غير موافق بشدة.",
        "correct": "",
        "selected": ""
    },
    {
        "id": 6,
        "type": 1,
        "question": "6.أندمج بسهولة في بيئة التعلم عندما أتعلم في مقرر البرمجه بلغة سكراتش.",
        "ansA": "موافق بشدة .",
        "ansB": "موافق.",
        "ansC": "محايد.",
        "ansD": "غير موافق.",
        "ansE": "غير موافق بشدة.",
        "correct": "",
        "selected": ""
    }
    ,
    {
        "id": 7,
        "type": 1,
        "question": "7. اجد صعوبة في تطوير مهاراتي عبر هذه البيئة.",
        "ansA": "موافق بشدة .",
        "ansB": "موافق.",
        "ansC": "محايد.",
        "ansD": "غير موافق.",
        "ansE": "غير موافق بشدة.",
        "correct": "",
        "selected": ""
    },
    {
        "id": 8,
        "type": 1,
        "question": "8. أحرص على الإنجاز لأحصل على تقييم افضل في المجموعه.",
        "ansA": "موافق بشدة .",
        "ansB": "موافق.",
        "ansC": "محايد.",
        "ansD": "غير موافق.",
        "ansE": "غير موافق بشدة.",
        "correct": "",
        "selected": ""
    },
    {
        "id": 9,
        "type": 1,
        "question": "9. تشجعني بيئه التعلم على متابعه الدروس بانتظام.",
        "ansA": "موافق بشدة .",
        "ansB": "موافق.",
        "ansC": "محايد.",
        "ansD": "غير موافق.",
        "ansE": "غير موافق بشدة.",
        "correct": "",
        "selected": ""
    },
    {
        "id": 10,
        "type": 1,
        "question": "10.انا غير مهتم بإتمام ما كلفت به في مقرر البرمجه بلغه سكراتش.",
        "ansA": "موافق بشدة .",
        "ansB": "موافق.",
        "ansC": "محايد.",
        "ansD": "غير موافق.",
        "ansE": "غير موافق بشدة.",
        "correct": "",
        "selected": ""
    },
    {
        "id": 11,
        "type": 1,
        "question": "11. أشارك مع فريقى في المهام بنشاط وفاعلية.",
        "ansA": "موافق بشدة .",
        "ansB": "موافق.",
        "ansC": "محايد.",
        "ansD": "غير موافق.",
        "ansE": "غير موافق بشدة.",
        "correct": "",
        "selected": ""
    },
    {
        "id": 12,
        "type": 1,
        "question": "12. يصعب علي إنجاز الأنشطة في الوقت المحدد لها.",
        "ansA": "موافق بشدة .",
        "ansB": "موافق.",
        "ansC": "محايد.",
        "ansD": "غير موافق.",
        "ansE": "غير موافق بشدة.",
        "correct": "",
        "selected": ""
    },
    {
        "id": 13,
        "type": 1,
        "question": "13. أشجع زملائي أثناء أداء المهام.",
        "ansA": "موافق بشدة .",
        "ansB": "موافق.",
        "ansC": "محايد.",
        "ansD": "غير موافق.",
        "ansE": "غير موافق بشدة.",
        "correct": "",
        "selected": ""
    },
    {
        "id": 14,
        "type": 1,
        "question": "14. تتنوع أدواري في المجموعه حسب النشاط الموكل إلي بالبيئة.",
        "ansA": "موافق بشدة .",
        "ansB": "موافق.",
        "ansC": "محايد.",
        "ansD": "غير موافق.",
        "ansE": "غير موافق بشدة.",
        "correct": "",
        "selected": ""
    },
    {
        "id": 15,
        "type": 1,
        "question": "15. اتواصل بفعالية مع فريقي ومعلمي أثناء التعلم.",
        "ansA": "موافق بشدة .",
        "ansB": "موافق.",
        "ansC": "محايد.",
        "ansD": "غير موافق.",
        "ansE": "غير موافق بشدة.",
        "correct": "",
        "selected": ""
    },
    {
        "id": 16,
        "type": 1,
        "question": "  16. أنجز الأنشطة لرغبتي فى الحصول علي المكافأت.",
        "ansA": "موافق بشدة .",
        "ansB": "موافق.",
        "ansC": "محايد.",
        "ansD": "غير موافق.",
        "ansE": "غير موافق بشدة.",
        "correct": "",
        "selected": ""
    },
    {
        "id": 17,
        "type": 1,
        "question": " 17.أشعر بخيبه الأمل إذا فشلت في تحقيق الأهداف",
        "ansA": "موافق بشدة .",
        "ansB": "موافق.",
        "ansC": "محايد.",
        "ansD": "غير موافق.",
        "ansE": "غير موافق بشدة.",
        "correct": "",
        "selected": ""
    },
    {
        "id": 18,
        "type": 1,
        "question": " 18. أشعر بالمتعة والسعاده عند نجاحى في تحدي المهام الصعبه في مقرر البرمجه بلغه سكراتش.",
        "ansA": "موافق بشدة .",
        "ansB": "موافق.",
        "ansC": "محايد.",
        "ansD": "غير موافق.",
        "ansE": "غير موافق بشدة.",
        "correct": "",
        "selected": ""
    },
    {
        "id": 19,
        "type": 1,
        "question": "19. أشعر بالملل فى التعلم برنامج سكراتش.",
        "ansA": "موافق بشدة .",
        "ansB": "موافق.",
        "ansC": "محايد.",
        "ansD": "غير موافق.",
        "ansE": "غير موافق بشدة.",
        "correct": "",
        "selected": ""
    },
    {
        "id": 20,
        "type": 1,
        "question": "20. أشعر بالتحدي فى حل الالغاز ببيئة التعلم.",
        "ansA": "موافق بشدة .",
        "ansB": "موافق.",
        "ansC": "محايد.",
        "ansD": "غير موافق.",
        "ansE": "غير موافق بشدة.",
        "correct": "",
        "selected": ""
    }
    ,
    {
        "id": 21,
        "type": 1,
        "question": " 21. أشعر باللامبالاة عند وجود أنشطة مطلوب تنفيذها داخل البيئة .",
        "ansA": "موافق بشدة .",
        "ansB": "موافق.",
        "ansC": "محايد.",
        "ansD": "غير موافق.",
        "ansE": "غير موافق بشدة.",
        "correct": "",
        "selected": ""
    }
    ,
    {
        "id": 22,
        "type": 1,
        "question": "22. أشعر بالحماس لدراسه برنامج سكراتش من اجل تحقيق نتائج جيده في لوحه الصدارة.",
        "ansA": "موافق بشدة .",
        "ansB": "موافق.",
        "ansC": "محايد.",
        "ansD": "غير موافق.",
        "ansE": "غير موافق بشدة.",
        "correct": "",
        "selected": ""
    } ,
    {
        "id": 23,
        "type": 1,
        "question": "23. بيئه التعلم ممتعه وجذابه.",
        "ansA": "موافق بشدة .",
        "ansB": "موافق.",
        "ansC": "محايد.",
        "ansD": "غير موافق.",
        "ansE": "غير موافق بشدة.",
        "correct": "",
        "selected": ""
    } ,
    {
        "id": 24,
        "type": 1,
        "question": "24.أستمتع بعرض إنجازاتى مع زملائي في الفصل.",
        "ansA": "موافق بشدة .",
        "ansB": "موافق.",
        "ansC": "محايد.",
        "ansD": "غير موافق.",
        "ansE": "غير موافق بشدة.",
        "correct": "",
        "selected": ""
    } ,
    {
        "id": 25,
        "type": 1,
        "question": "25. أشعر بالرضا فى التعلم برنامج سكراتش من هذه البيئة.",
        "ansA": "موافق بشدة .",
        "ansB": "موافق.",
        "ansC": "محايد.",
        "ansD": "غير موافق.",
        "ansE": "غير موافق بشدة.",
        "correct": "",
        "selected": ""
    } ,
    {
        "id": 26,
        "type": 1,
        "question": "26.أشعر بالقلق اثناء التعلم برنامج سكراتش من هذه البيئة.",
        "ansA": "موافق بشدة .",
        "ansB": "موافق.",
        "ansC": "محايد.",
        "ansD": "غير موافق.",
        "ansE": "غير موافق بشدة.",
        "correct": "",
        "selected": ""
    } ,
    {
        "id": 27,
        "type": 1,
        "question": "27.أشعر بالاجهاد اثناء اداء الانشطه في البيئة .",
        "ansA": "موافق بشدة .",
        "ansB": "موافق.",
        "ansC": "محايد.",
        "ansD": "غير موافق.",
        "ansE": "غير موافق بشدة.",
        "correct": "",
        "selected": ""
    } ,
    {
        "id": 28,
        "type": 1,
        "question": "28. اشعر بعدم الرغبة في التعلم بهذه الطريقه في المواد الدراسيه الأخرى.",
        "ansA": "موافق بشدة .",
        "ansB": "موافق.",
        "ansC": "محايد.",
        "ansD": "غير موافق.",
        "ansE": "غير موافق بشدة.",
        "correct": "",
        "selected": ""
    } ,
    {
        "id": 29,
        "type": 1,
        "question": "29. أشعر بأن بيئه التعلم تستغل وقت التعلم بشكل افضل عن التعلم بالطريقة التقليدية.  ",
        "ansA": "موافق بشدة .",
        "ansB": "موافق.",
        "ansC": "محايد.",
        "ansD": "غير موافق.",
        "ansE": "غير موافق بشدة.",
        "correct": "",
        "selected": ""
    } 
]